imbalanced_databases/__init__.py
imbalanced_databases/_imbalanced_databases.py
imbalanced_databases/data/abalone-17_vs_7-8-9-10/abalone-17_vs_7-8-9-10-names.txt
imbalanced_databases/data/abalone-17_vs_7-8-9-10/abalone-17_vs_7-8-9-10.dat
imbalanced_databases/data/abalone-17_vs_7-8-9-10/abalone-17_vs_7-8-9-10.dat.bak
imbalanced_databases/data/abalone-17_vs_7-8-9-10/test.dat
imbalanced_databases/data/abalone-17_vs_7-8-9-10/test.dat.bak
imbalanced_databases/data/abalone-19_vs_10-11-12-13/abalone-19_vs_10-11-12-13-names.txt
imbalanced_databases/data/abalone-19_vs_10-11-12-13/abalone-19_vs_10-11-12-13.dat
imbalanced_databases/data/abalone-19_vs_10-11-12-13/abalone-19_vs_10-11-12-13.dat.bak
imbalanced_databases/data/abalone-20_vs_8-9-10/abalone-20_vs_8-9-10-names.txt
imbalanced_databases/data/abalone-20_vs_8-9-10/abalone-20_vs_8-9-10.dat
imbalanced_databases/data/abalone-20_vs_8-9-10/abalone-20_vs_8-9-10.dat.bak
imbalanced_databases/data/abalone-21_vs_8/abalone-21_vs_8-names.txt
imbalanced_databases/data/abalone-21_vs_8/abalone-21_vs_8.dat
imbalanced_databases/data/abalone-21_vs_8/abalone-21_vs_8.dat.bak
imbalanced_databases/data/abalone-3_vs_11/abalone-3_vs_11-names.txt
imbalanced_databases/data/abalone-3_vs_11/abalone-3_vs_11.dat
imbalanced_databases/data/abalone-3_vs_11/abalone-3_vs_11.dat.bak
imbalanced_databases/data/abalone19/abalone19-names.txt
imbalanced_databases/data/abalone19/abalone19.dat
imbalanced_databases/data/abalone19/abalone19.dat.bak
imbalanced_databases/data/abalone9-18/abalone9-18-names.txt
imbalanced_databases/data/abalone9-18/abalone9-18.dat
imbalanced_databases/data/abalone9-18/abalone9-18.dat.bak
imbalanced_databases/data/ada/README.md
imbalanced_databases/data/ada/ada.param
imbalanced_databases/data/ada/ada_train.data
imbalanced_databases/data/ada/ada_train.labels
imbalanced_databases/data/car-good/car-good-names.txt
imbalanced_databases/data/car-good/car-good.dat
imbalanced_databases/data/car-good/car-good.dat.bak
imbalanced_databases-0.1.1.dist-info/METADATA
imbalanced_databases-0.1.1.dist-info/WHEEL
imbalanced_databases-0.1.1.dist-info/top_level.txt
imbalanced_databases-0.1.1.dist-info/RECORD
