Metadata-Version: 2.1
Name: imbalanced-databases
Version: 0.1.1
Summary: imbalanced databases
Home-page: http://github.com/gykovacs/imbalanced_databases
Author: Gyorgy Kovacs
Author-email: gyuriofkovacs@gmail.com
License: MIT
Platform: UNKNOWN
Classifier: Development Status :: 3 - Alpha
Classifier: License :: OSI Approved :: MIT License
Classifier: Programming Language :: Python
Classifier: Topic :: Scientific/Engineering :: Artificial Intelligence
Requires-Dist: numpy
Requires-Dist: pandas
Requires-Dist: scipy
Requires-Dist: sklearn
